fiscalyear.py
fiscalyear-0.3.2.dist-info/LICENSE
fiscalyear-0.3.2.dist-info/METADATA
fiscalyear-0.3.2.dist-info/WHEEL
fiscalyear-0.3.2.dist-info/top_level.txt
fiscalyear-0.3.2.dist-info/RECORD
